<annotation>
	<folder></folder>
	<filename>PLATELET_293960_jpg_jpg.rf.b700315b10907a7c47cac57a16a3bd9a.jpg</filename>
	<path>PLATELET_293960_jpg_jpg.rf.b700315b10907a7c47cac57a16a3bd9a.jpg</path>
	<source>
		<database>roboflow.com</database>
	</source>
	<size>
		<width>840</width>
		<height>840</height>
		<depth>3</depth>
	</size>
	<segmented>0</segmented>
	<object>
		<name>platelets</name>
		<pose>Unspecified</pose>
		<truncated>0</truncated>
		<difficult>0</difficult>
		<occluded>0</occluded>
		<bndbox>
			<xmin>328</xmin>
			<xmax>524</xmax>
			<ymin>339</ymin>
			<ymax>512</ymax>
		</bndbox>
	</object>
	<object>
		<name>platelets</name>
		<pose>Unspecified</pose>
		<truncated>0</truncated>
		<difficult>0</difficult>
		<occluded>0</occluded>
		<bndbox>
			<xmin>267</xmin>
			<xmax>363</xmax>
			<ymin>71</ymin>
			<ymax>175</ymax>
		</bndbox>
	</object>
</annotation>
