<annotation>
	<folder></folder>
	<filename>PLATELET_558803_jpg_jpg.rf.d73813f7c4b441c18ae9c1e3dc5d405e.jpg</filename>
	<path>PLATELET_558803_jpg_jpg.rf.d73813f7c4b441c18ae9c1e3dc5d405e.jpg</path>
	<source>
		<database>roboflow.com</database>
	</source>
	<size>
		<width>840</width>
		<height>840</height>
		<depth>3</depth>
	</size>
	<segmented>0</segmented>
	<object>
		<name>platelets</name>
		<pose>Unspecified</pose>
		<truncated>0</truncated>
		<difficult>0</difficult>
		<occluded>0</occluded>
		<bndbox>
			<xmin>330</xmin>
			<xmax>519</xmax>
			<ymin>371</ymin>
			<ymax>552</ymax>
		</bndbox>
	</object>
	<object>
		<name>platelets</name>
		<pose>Unspecified</pose>
		<truncated>0</truncated>
		<difficult>0</difficult>
		<occluded>0</occluded>
		<bndbox>
			<xmin>330</xmin>
			<xmax>395</xmax>
			<ymin>536</ymin>
			<ymax>605</ymax>
		</bndbox>
	</object>
</annotation>
